{"id": 11002, "level": "N1", "title": "\u307e\u3044\u3068\u3057\u3066", "means": [{"id": 11002100, "format": "5YuV6Kme6L6e5pu45b2i77yL44G+44GE44Go44GX44Gm", "mean": ["44Gq44GE44KI44GG44Gr44Go5oCd44Gj44GmwqDCoOS4jeWBmu+9niA="], "type": ["\u5176\u5b83"], "examples": [{"id": 22327, "ruby": "\u30df\u30b9\u3092<ruby><rb>\u72af</rb><rt>\u304a\u304b</rt></ruby>\u3059\u307e\u3044\u3068\u3057\u3066<ruby><rb>\u5fc5\u6b7b</rb><rt>\u3072\u3063\u3057</rt></ruby>\u306b\u306a\u3063\u3066\u3044\u308b\u3002", "explain": "\u62fc\u547d\u52aa\u529b\u4e0d\u72af\u9519\u8bef\u3002", "other": ""}]}]}