{"id": 11123, "level": "N4", "title": "\uff5e\u601d\u3046", "means": [{"id": 11123100, "format": "44KjQeOBjyvmgJ3jgYYv44Gv5oCd44KP44Gq44GEIOODikHjgasr5oCd44GGL+OBr+aAneOCj+OBquOBhCA=", "mean": ["wqDCoOaEn+iniX7vvIzmsqHmnInmhJ/op4l+IA=="], "type": ["\u63a8\u91cf"], "examples": [{"id": 22620, "ruby": "<ruby><rb>\u9ad8\u5d0e</rb><rt>\u305f\u304b\u3055\u304d</rt></ruby>\u3055\u3093\u306f\u30da\u30c3\u30c8\u306e<ruby><rb>\u6b7b</rb><rt>\u3057</rt></ruby>\u3092\u3068\u3066\u3082<ruby><rb>\u60b2</rb><rt>\u304b\u306a</rt></ruby>\u3057\u304f<ruby><rb>\u601d</rb><rt>\u304a\u3082</rt></ruby>\u3063\u3066\u3044\u307e\u3059\u3002", "explain": "\u9ad8\u5d0e\u4e3a\u5ba0\u7269\u4e4b\u6b7b\u611f\u5230\u5f88\u96be\u8fc7\u3002", "other": ""}, {"id": 22621, "ruby": "\u304a<ruby><rb>\u76ee</rb><rt>\u3081</rt></ruby>\u306b\u304b\u304b\u308c\u3070\u3001\u3046\u308c\u3057\u304f<ruby><rb>\u601d</rb><rt>\u304a\u3082</rt></ruby>\u3044\u307e\u3059\u3002", "explain": "\u5982\u679c\u80fd\u89c1\u5230\u60a8\uff0c\u6211\u4f1a\u5f88\u9ad8\u5174\u7684\u3002", "other": ""}, {"id": 22622, "ruby": "<ruby><rb>\u5c71\u7530</rb><rt>\u3084\u307e\u3060</rt></ruby><ruby><rb>\u6559\u6388</rb><rt>\u304d\u3087\u3046\u3058\u3085</rt></ruby>\u306e<ruby><rb>\u8b1b\u7fa9</rb><rt>\u3053\u3046\u304e</rt></ruby>\u3092<ruby><rb>\u805e</rb><rt>\u304d</rt></ruby>\u304f\u3053\u3068\u304c\u3067\u304d\u3066\u3001<ruby><rb>\u672c\u5f53</rb><rt>\u307b\u3093\u3068\u3046</rt></ruby>\u306b<ruby><rb>\u5e78</rb><rt>\u3057\u3042\u308f</rt></ruby>\u305b\u306b<ruby><rb>\u601d</rb><rt>\u304a\u3082</rt></ruby>\u3044\u307e\u3059\u3002", "explain": "\u80fd\u8046\u542c\u5c71\u7530\u6559\u6388\u7684\u8bfe\uff0c\u6211\u6df1\u611f\u8363\u5e78\u3002", "other": ""}]}]}