{"id": 11518, "level": "N4", "title": "\u3084\u3059\u3044\u3067\u3059/\u306b\u304f\u3044\u3067\u3059", "means": [{"id": 11518100, "format": "VuOBvuOBmSvjgoTjgZnjgYTjgafjgZkv44Gr44GP44GE44Gn44GZ", "mean": ["wqDCoH7lrrnmmJMv6Zq+IA=="], "type": ["\u69d8\u5b50\u30fb\u72b6\u614b"], "examples": [{"id": 24456, "ruby": "\u3053\u306e\u30d1\u30bd\u30b3\u30f3\u306f<ruby><rb>\u4f7f</rb><rt>\u3064\u304b</rt></ruby>\u3044\u3084\u3059\u3044\u3067\u3059\u3002", "explain": "\u8fd9\u4e2a\u8ba1\u7b97\u673a\u5f88\u597d\u7528\u3002", "other": ""}, {"id": 24457, "ruby": "<ruby><rb>\u6771\u4eac</rb><rt>\u3068\u3046\u304d\u3087\u3046</rt></ruby>\u306f<ruby><rb>\u4f4f</rb><rt>\u3059</rt></ruby>\u307f\u306b\u304f\u3044\u3067\u3059\u3002", "explain": "\u4e1c\u4eac\u4e0d\u5bb9\u6613\u5c45\u4f4f\u3002", "other": ""}]}, {"id": 11518101, "format": "VuOBvuOBmSvjgoTjgZnjgYTjgafjgZkv44Gr44GP44GE44Gn44GZ", "mean": ["wqDCoH7lrrnmmJMv6Zq+IA=="], "type": ["\u69d8\u5b50\u30fb\u72b6\u614b"], "examples": [{"id": 24458, "ruby": "<ruby><rb>\u767d</rb><rt>\u3057\u308d</rt></ruby>\u3044\u30b7\u30e3\u30c4\u306f<ruby><rb>\u6c5a</rb><rt>\u3088\u3054</rt></ruby>\u308c\u3084\u3059\u3044\u3067\u3059\u3002", "explain": "\u767d\u886c\u886b\u5bb9\u6613\u810f\u3002", "other": ""}, {"id": 24459, "ruby": "<ruby><rb>\u96e8</rb><rt>\u3042\u3081</rt></ruby>\u306e<ruby><rb>\u65e5</rb><rt>\u3072</rt></ruby>\u306f<ruby><rb>\u6d17\u6fef</rb><rt>\u305b\u3093\u305f\u304f</rt></ruby><ruby><rb>\u7269</rb><rt>\u3076\u3064</rt></ruby>\u304c<ruby><rb>\u4e7e</rb><rt>\u304b\u308f</rt></ruby>\u304d\u306b\u304f\u3044\u3067\u3059\u3002", "explain": "\u4e0b\u96e8\u5929\u6d17\u7684\u4e1c\u897f\u4e0d\u5bb9\u6613\u5e72\u3002", "other": ""}]}]}