{"id": 11513, "level": "N4", "title": "\u305f\u3089", "means": [{"id": 11513100, "format": "5bCP5Y+lMe+8i+OBn+OCie+8jO+8i+Wwj+WPpTI=", "mean": [""], "type": ["\u6761\u4ef6"], "examples": [{"id": 24448, "ruby": "<ruby><rb>\u660e\u65e5</rb><rt>\u3042\u3057\u305f</rt></ruby><ruby><rb>\u96e8</rb><rt>\u3042\u3081</rt></ruby>\u304c<ruby><rb>\u964d</rb><rt>\u3075</rt></ruby>\u3063\u305f\u3089\u3001\u30de\u30e9\u30bd\u30f3<ruby><rb>\u5927\u4f1a</rb><rt>\u305f\u3044\u304b\u3044</rt></ruby>\u306f<ruby><rb>\u4e2d\u6b62</rb><rt>\u3061\u3085\u3046\u3057</rt></ruby>\u3067\u3059\u3002", "explain": "\u660e\u5929\u8981\u662f\u4e0b\u96e8\uff0c\u9a6c\u62c9\u677e\u5927\u4f1a\u5c31\u4e0d\u641e\u4e86", "other": ""}, {"id": 24449, "ruby": "<ruby><rb>\u5bd2</rb><rt>\u3055\u3080</rt></ruby>\u304b\u3063\u305f\u3089\u3001<ruby><rb>\u7a93</rb><rt>\u307e\u3069</rt></ruby>\u3092<ruby><rb>\u9589</rb><rt>\u3057</rt></ruby>\u3081\u3066\u304f\u3060\u3055\u3044\u3002", "explain": "\u51b7\u7684\u8bdd\uff0c\u5c31\u628a\u7a97\u6237\u5173\u4e0a\u3002", "other": ""}, {"id": 24450, "ruby": "<ruby><rb>\u660e\u65e5</rb><rt>\u3042\u3057\u305f</rt></ruby><ruby><rb>\u96e8</rb><rt>\u3042\u3081</rt></ruby>\u3067\u306a\u304b\u3063\u305f\u3089\u3001\u30cf\u30a4\u30ad\u30f3\u30b0\u306b<ruby><rb>\u884c</rb><rt>\u3044</rt></ruby>\u304d\u307e\u3059\u3002", "explain": "\u660e\u5929\u8981\u662f\u4e0d\u4e0b\u96e8\uff0c\u5c31\u53bb\u90ca\u6e38\u3002", "other": ""}]}]}